frame_stamp/__init__.py
frame_stamp/__version__.py
frame_stamp/stamp.py
frame_stamp/bin/open_viewer.sh
frame_stamp/fonts/OpenSans.ttf
frame_stamp/fonts/OpenSansBold.ttf
frame_stamp/fonts/OpenSansSemiBold.ttf
frame_stamp/fonts/Vera.ttf
frame_stamp/fonts/VeraMono.ttf
frame_stamp/fonts/VeraMonoBold.ttf
frame_stamp/resources/icon.png
frame_stamp/resources/icon.svg
frame_stamp/shape/__init__.py
frame_stamp/shape/base_shape.py
frame_stamp/shape/circle.py
frame_stamp/shape/column.py
frame_stamp/shape/grid.py
frame_stamp/shape/image.py
frame_stamp/shape/label.py
frame_stamp/shape/line.py
frame_stamp/shape/polygon.py
frame_stamp/shape/rect.py
frame_stamp/shape/row.py
frame_stamp/shape/tile.py
frame_stamp/utils/__init__.py
frame_stamp/utils/b64.py
frame_stamp/utils/background_grig.py
frame_stamp/utils/batch.py
frame_stamp/utils/exceptions.py
frame_stamp/utils/geometry_tools.py
frame_stamp/utils/image_tools.py
frame_stamp/utils/jsonc.py
frame_stamp/utils/point.py
frame_stamp/utils/pytemplate.py
frame_stamp/utils/rect.py
frame_stamp/utils/render_svg.py
frame_stamp/viewer/__init__.py
frame_stamp/viewer/canvas.py
frame_stamp/viewer/create_grid_dialog.py
frame_stamp/viewer/default_template.py
frame_stamp/viewer/dialog.py
frame_stamp/viewer/watch.py
frame_stamp-0.1.9.dist-info/METADATA
frame_stamp-0.1.9.dist-info/WHEEL
frame_stamp-0.1.9.dist-info/RECORD
