Metadata-Version: 2.4
Name: frame-stamp
Version: 0.1.9
Summary: Adding technical information to images using a template.
Author-email: paulwinex <paulwinex@gmail.com>
Requires-Python: <3.13,>=3.9
Requires-Dist: pillow>=11.3.0
Requires-Dist: pyyaml<7,>=6.0.2
Requires-Dist: recommonmark<0.8,>=0.7.1
Provides-Extra: pyside
Requires-Dist: pyside6==6.8.1; extra == 'pyside'
Provides-Extra: svg
Requires-Dist: cairosvg<3,>=2.7.1; extra == 'svg'
